pyaes/__init__.py
pyaes/aes.py
pyaes/blockfeeder.py
pyaes/util.py
pyaes_whl-1.6.1.dist-info/licenses/LICENSE.txt
pyaes_whl-1.6.1.dist-info/METADATA
pyaes_whl-1.6.1.dist-info/WHEEL
pyaes_whl-1.6.1.dist-info/top_level.txt
pyaes_whl-1.6.1.dist-info/RECORD
