Metadata-Version: 2.4
Name: pyaes-whl
Version: 1.6.1
Summary: Pure-Python Implementation of the AES block-cipher and common modes of operation
Author-email: Richard Moore <pyaes@ricmoo.com>
License: MIT License
Project-URL: Homepage, https://github.com/ricmoo/pyaes
Keywords: aes,encryption,cryptography
Classifier: Topic :: Security :: Cryptography
Classifier: License :: OSI Approved :: MIT License
License-File: LICENSE.txt
Dynamic: license-file
